Metadata-Version: 2.1
Name: django-template-cli
Version: 2020.7.1
Summary: CLI tool to render django template files
Home-page: https://github.com/andrewp-as-is/django-template-cli.py
License: Unlicense
Keywords: django template
Platform: UNKNOWN
Classifier: Framework :: Django
Classifier: License :: Public Domain
Classifier: Operating System :: Unix
Classifier: Programming Language :: Python :: 3
Classifier: Programming Language :: Unix Shell
Classifier: Topic :: Utilities
